eventail/__init__.py
eventail/batch_processor.py
eventail/gelf.py
eventail/log_criticity.py
eventail/py.typed
eventail/sync_publisher.py
eventail/tmp_store.py
eventail/async_service/__init__.py
eventail/async_service/pika/__init__.py
eventail/async_service/pika/base.py
eventail/async_service/pika/supervisor.py
eventail-2.3.6.data/scripts/inspect_queue.py
eventail-2.3.6.data/scripts/logger.py
eventail-2.3.6.data/scripts/monitor.py
eventail-2.3.6.data/scripts/publish_configuration.py
eventail-2.3.6.data/scripts/publish_event.py
eventail-2.3.6.data/scripts/resurrect.py
eventail-2.3.6.data/scripts/send_command.py
eventail-2.3.6.dist-info/licenses/LICENSE
eventail-2.3.6.dist-info/METADATA
eventail-2.3.6.dist-info/WHEEL
eventail-2.3.6.dist-info/top_level.txt
eventail-2.3.6.dist-info/RECORD
