Metadata-Version: 2.4
Name: eventail
Version: 2.3.6
Summary: A base class and utilities for AM service architecture
Home-page: https://github.com/allo-media/eventail
Author: Allo-Media
Author-email: dev@allo-media.fr
License: MIT
Classifier: Development Status :: 5 - Production/Stable
Classifier: License :: OSI Approved :: MIT License
Classifier: Programming Language :: Python :: 3.8
Classifier: Programming Language :: Python :: 3.9
Classifier: Programming Language :: Python :: 3.10
Classifier: Programming Language :: Python :: 3.11
Classifier: Programming Language :: Python :: 3.12
Classifier: Programming Language :: Python :: 3.13
Classifier: Intended Audience :: Developers
Classifier: Operating System :: POSIX :: Linux
Classifier: Topic :: Software Development
Requires-Python: >=3.8
License-File: LICENSE
Requires-Dist: pika>=1.2.0
Requires-Dist: cbor2
Requires-Dist: redis>=4.5.4
Provides-Extra: synchronous
Requires-Dist: kombu; extra == "synchronous"
Provides-Extra: test
Requires-Dist: tox; extra == "test"
Dynamic: author
Dynamic: author-email
Dynamic: classifier
Dynamic: description
Dynamic: description-content-type
Dynamic: home-page
Dynamic: license
Dynamic: license-file
Dynamic: provides-extra
Dynamic: requires-dist
Dynamic: requires-python
Dynamic: summary
